zrb/__init__.py
zrb/__main__.py
zrb/attr/type.py
zrb/builtin/__init__.py
zrb/builtin/base64.py
zrb/builtin/git.py
zrb/builtin/git_subtree.py
zrb/builtin/group.py
zrb/builtin/http.py
zrb/builtin/jwt.py
zrb/builtin/llm/chat.py
zrb/builtin/md5.py
zrb/builtin/project/add/fastapp/fastapp_input.py
zrb/builtin/project/add/fastapp/fastapp_task.py
zrb/builtin/project/add/fastapp/fastapp_template/my_app_name/.coveragerc
zrb/builtin/project/add/fastapp/fastapp_template/my_app_name/.flake8
zrb/builtin/project/add/fastapp/fastapp_template/my_app_name/.gitignore
zrb/builtin/project/add/fastapp/fastapp_template/my_app_name/README.md
zrb/builtin/project/add/fastapp/fastapp_template/my_app_name/_zrb/column/add_column_task.py
zrb/builtin/project/add/fastapp/fastapp_template/my_app_name/_zrb/column/add_column_util.py
zrb/builtin/project/add/fastapp/fastapp_template/my_app_name/_zrb/config.py
zrb/builtin/project/add/fastapp/fastapp_template/my_app_name/_zrb/entity/add_entity_task.py
zrb/builtin/project/add/fastapp/fastapp_template/my_app_name/_zrb/entity/add_entity_util.py
zrb/builtin/project/add/fastapp/fastapp_template/my_app_name/_zrb/entity/template/app_template/module/gateway/view/content/my-module/my-entity.html
zrb/builtin/project/add/fastapp/fastapp_template/my_app_name/_zrb/entity/template/app_template/module/my_module/service/my_entity/my_entity_service.py
zrb/builtin/project/add/fastapp/fastapp_template/my_app_name/_zrb/entity/template/app_template/module/my_module/service/my_entity/my_entity_service_factory.py
zrb/builtin/project/add/fastapp/fastapp_template/my_app_name/_zrb/entity/template/app_template/module/my_module/service/my_entity/repository/my_entity_db_repository.py
zrb/builtin/project/add/fastapp/fastapp_template/my_app_name/_zrb/entity/template/app_template/module/my_module/service/my_entity/repository/my_entity_repository.py
zrb-2.0.15.dist-info/METADATA
zrb-2.0.15.dist-info/WHEEL
zrb-2.0.15.dist-info/entry_points.txt
zrb-2.0.15.dist-info/RECORD
