Metadata-Version: 2.4
Name: zrb
Version: 2.0.15
Summary: Your Automation Powerhouse
License: AGPL-3.0-or-later
Keywords: Automation,Task Runner,Code Generator,Monorepo,Low Code
Author: Go Frendi Gunawan
Author-email: gofrendiasgard@gmail.com
Requires-Python: >=3.11.0,<4.0.0
Classifier: License :: OSI Approved :: GNU Affero General Public License v3 or later (AGPLv3+)
Classifier: Programming Language :: Python :: 3
Classifier: Programming Language :: Python :: 3.11
Classifier: Programming Language :: Python :: 3.12
Classifier: Programming Language :: Python :: 3.13
Classifier: Programming Language :: Python :: 3.14
Provides-Extra: all
Provides-Extra: anthropic
Provides-Extra: bedrock
Provides-Extra: cohere
Provides-Extra: google
Provides-Extra: groq
Provides-Extra: huggingface
Provides-Extra: mistral
Provides-Extra: playwright
Provides-Extra: rag
Provides-Extra: vertexai
Requires-Dist: anthropic (>=0.75.0) ; extra == "anthropic" or extra == "all"
Requires-Dist: beautifulsoup4 (>=4.14.2,<5.0.0)
Requires-Dist: black (>=25.11.0,<26.0.0)
Requires-Dist: boto3 (>=1.42.14) ; extra == "bedrock"
Requires-Dist: chromadb (>=1.3.5,<2.0.0) ; extra == "rag" or extra == "all"
Requires-Dist: cohere (>=5.18.0) ; extra == "cohere" or extra == "all"
Requires-Dist: fastapi[standard] (>=0.123.10,<0.124.0)
Requires-Dist: google-auth (>=2.36.0) ; extra == "vertexai" or extra == "all"
Requires-Dist: google-genai (>=1.56.0) ; extra == "google" or extra == "all"
Requires-Dist: groq (>=0.25.0) ; extra == "groq" or extra == "all"
Requires-Dist: huggingface-hub[inference] (>=0.33.5,<1.0.0) ; extra == "huggingface"
Requires-Dist: isort (>=7.0.0,<8.0.0)
Requires-Dist: libcst (>=1.8.6,<2.0.0)
Requires-Dist: markdownify (>=1.2.2,<2.0.0)
Requires-Dist: mcp (>1.25.0,<2.0)
Requires-Dist: mistralai (>=1.9.11) ; extra == "mistral"
Requires-Dist: openai (>=2.11.0)
Requires-Dist: pdfplumber (>=0.11.7,<0.12.0)
Requires-Dist: playwright (>=1.56.0,<2.0.0) ; extra == "playwright" or extra == "all"
Requires-Dist: prompt-toolkit (>=3)
Requires-Dist: psutil (>=7.0.0,<8.0.0)
Requires-Dist: pydantic-ai-slim (>=1.48.0,<1.49.0)
Requires-Dist: pyjwt (>=2.10.1,<3.0.0)
Requires-Dist: pyperclip (>=1.11.0,<2.0.0)
Requires-Dist: python-dotenv (>=1.1.1,<2.0.0)
Requires-Dist: python-jose[cryptography] (>=3.5.0,<4.0.0)
Requires-Dist: pyyaml (>=6.0.3,<7.0.0)
Requires-Dist: requests (>=2.32.5,<3.0.0)
Requires-Dist: rich (>=13)
Requires-Dist: tiktoken (>=0.12.0,<0.13.0)
Requires-Dist: ulid-py (>=1.1.0,<2.0.0)
Project-URL: Documentation, https://github.com/state-alchemists/zrb
Project-URL: Homepage, https://github.com/state-alchemists/zrb
Project-URL: Repository, https://github.com/state-alchemists/zrb
